revenium_middleware_core/__init__.py
revenium_middleware_core/metering.py
revenium_middleware_core-0.2.1.dist-info/licenses/LICENSE
revenium_middleware_core-0.2.1.dist-info/METADATA
revenium_middleware_core-0.2.1.dist-info/WHEEL
revenium_middleware_core-0.2.1.dist-info/top_level.txt
revenium_middleware_core-0.2.1.dist-info/RECORD
