Metadata-Version: 2.4
Name: revenium-middleware-core
Version: 0.2.1
Summary: A Python library that provides core functionality to send AI metering data to Revenium.
Author-email: Revenium <info@revenium.io>
License: Apache License 2.0
Project-URL: Homepage, https://github.com/revenium/revenium-middleware-core-python
Project-URL: Bug Tracker, https://github.com/revenium/revenium-middleware-core-python/issues
Project-URL: Documentation, https://github.com/revenium/revenium-middleware-core-python/blob/main/README.md
Keywords: middleware,logging,token-usage,metering,revenium
Classifier: Development Status :: 4 - Beta
Classifier: Programming Language :: Python :: 3
Classifier: Programming Language :: Python :: 3.8
Classifier: Programming Language :: Python :: 3.9
Classifier: Programming Language :: Python :: 3.10
Classifier: Programming Language :: Python :: 3.11
Classifier: Programming Language :: Python :: 3.12
Classifier: License :: OSI Approved :: Apache Software License
Classifier: Operating System :: OS Independent
Classifier: Intended Audience :: Developers
Classifier: Topic :: Software Development :: Libraries :: Python Modules
Requires-Python: >=3.8
License-File: LICENSE
Requires-Dist: revenium_metering
Provides-Extra: dev
Requires-Dist: pytest>=7.0.0; extra == "dev"
Requires-Dist: pytest-cov; extra == "dev"
Requires-Dist: flake8; extra == "dev"
Requires-Dist: black; extra == "dev"
Requires-Dist: mypy; extra == "dev"
Requires-Dist: freezegun; extra == "dev"
Dynamic: license-file
